rsome/__init__.py
rsome/clp_solver.py
rsome/cpt_solver.py
rsome/cpt_solver_bkp.py
rsome/cpx_solver.py
rsome/deco.py
rsome/dro.py
rsome/eco_solver.py
rsome/gcp.py
rsome/grb_solver.py
rsome/lp.py
rsome/lpg_solver.py
rsome/math.py
rsome/msk_solver.py
rsome/ort_solver.py
rsome/py.typed
rsome/ro.py
rsome/socp.py
rsome/subroutines.py
rsome/this.py
rsome-1.3.0.dist-info/LICENSE.md
rsome-1.3.0.dist-info/METADATA
rsome-1.3.0.dist-info/WHEEL
rsome-1.3.0.dist-info/top_level.txt
rsome-1.3.0.dist-info/RECORD
