Metadata-Version: 2.1
Name: rsome
Version: 1.3.0
Summary: Robust Stochastic Optimization Made Easy
Author: Peng Xiong
License: GPL-3.0
Platform: linux
Platform: osx
Platform: win64
Classifier: Programming Language :: Python :: 3.8
Classifier: Programming Language :: Python :: 3.9
Classifier: Programming Language :: Python :: 3.10
Classifier: Programming Language :: Python :: 3.11
Classifier: Programming Language :: Python :: 3.12
Requires-Python: >=3.8
License-File: LICENSE.md
Requires-Dist: numpy (>=1.20.0)
Requires-Dist: scipy (>=1.9.0)
Requires-Dist: pandas (>=0.25.0)
Provides-Extra: testing
Requires-Dist: pytest (>=6.0) ; extra == 'testing'
Requires-Dist: pytest-cov (>=2.0) ; extra == 'testing'
Requires-Dist: mypy (>=0.910) ; extra == 'testing'
Requires-Dist: flake8 (>=3.9) ; extra == 'testing'
Requires-Dist: tox (>=3.24) ; extra == 'testing'
